AUTHORS.rst
HISTORY.rst
LICENSE
MANIFEST.in
README.rst
setup.cfg
setup.py
wunderpy2/__init__.py
wunderpy2/endpoint_helpers.py
wunderpy2/exceptions.py
wunderpy2/lists_endpoint.py
wunderpy2/model.py
wunderpy2/notes_endpoint.py
wunderpy2/positions_endpoints.py
wunderpy2/subtasks_endpoint.py
wunderpy2/tasks_endpoint.py
wunderpy2/wunderapi.py
wunderpy2/wunderclient.py
wunderpy2_python_3_fixes.egg-info/PKG-INFO
wunderpy2_python_3_fixes.egg-info/SOURCES.txt
wunderpy2_python_3_fixes.egg-info/dependency_links.txt
wunderpy2_python_3_fixes.egg-info/requires.txt
wunderpy2_python_3_fixes.egg-info/top_level.txt